{
  "users": {
    "greg|austinpwr@zohomail.eu": {
      "sent_ids": [
        "ansible_jinja2_filters",
        "infra_shutdown_verify_state",
        "bash_set_strict",
        "ansible_vault_use_playbook",
        "agile_user_story_format",
        "agile_roles_scrum",
        "ansible_pro_overlay_network_stack",
        "ansible_pro_swarm_no_container_name",
        "aws_least_privilege",
        "ansible_pro_vault_playbook_run",
        "aws_s3_public_warning",
        "agile_backlog_structure",
        "aws_cli_security_tip",
        "ansible_install_ubuntu",
        "aws_s3_upload_command",
        "ansible_register_condition",
        "ansible_lint_check",
        "ansible_pro_swarm_inventory_groups",
        "ansible_adv_stack_deploy_registry_auth",
        "aws_cli_configure_command",
        "aws_iam_admin_warning",
        "aws_route_table_command",
        "agile_user_story_format_b",
        "aws_iam_attach_role_policy",
        "ansible_terraform_inventory_chain",
        "aws_concepts_shared_responsibility_warning",
        "ansible_role_init",
        "ansible_pro_swarm_stack_deploy",
        "aws_elb_command",
        "aws_s3_lifecycle_tip",
        "aws_ec2_open_port_warning",
        "aws_iam_cli_list_users",
        "aws_rds_command",
        "agile_scrum_sprint_cycle",
        "ansible_pro_overlay_external_network",
        "aws_cli_access_denied_error",
        "terraform_plan_command",
        "ansible_adv_idempotence_best_practices",
        "ansible_pro_swarm_inventory_groups_b",
        "aws_iam_cli_list_policies",
        "aws_ec2_user_data_tip",
        "ansible_pro_private_image_tag",
        "aws_cloudwatch_command",
        "ansible_install_ppa",
        "aws_logs_tip",
        "ansible_playbook_run",
        "azure_vm_managed_identity",
        "aws_ec2_launch_command",
        "cron_redirection_logs",
        "aws_network_debug_error",
        "agile_avantages_limites",
        "ansible_adv_docker_login_idempotent_b",
        "aws_ec2_ssh_error",
        "aws_ec2_ssh_port_closed_warning",
        "agile_avantages_limites_b"
      ],
      "cycle": 1,
      "last_sent": "2026-04-11"
    },
    "greg_sql|austinpwr@zohomail.eu": {
      "sent_ids": [
        "sql_definition_langage",
        "sql_cle_etrangere_relation",
        "sql_select_colonnes",
        "sql_order_by_limit_top",
        "sql_nosql_superadmin_warning",
        "sql_create_view",
        "sql_float_argent_interdit",
        "sql_bind_address_tip",
        "sql_select_star_warning",
        "sql_cle_primaire_proprietes",
        "sql_create_index",
        "sql_transaction_begin_commit",
        "sql_create_table_primary_key"
      ],
      "cycle": 1,
      "last_sent": "2026-04-11"
    },
    "greg_aws|austinpwr@zohomail.eu": {
      "sent_ids": [
        "aws_concepts_service_models_examples",
        "aws_iam_credential_report",
        "aws_ec2_ssh_port_closed_warning",
        "aws_iam_cli_list_users",
        "aws_iam_definition",
        "aws_concepts_iaas_vs_paas_choice",
        "aws_ec2_launch_command",
        "aws_iam_admin_warning",
        "aws_iam_attach_role_policy",
        "aws_ec2_run_instances",
        "aws_concepts_region_az_concept",
        "aws_concepts_shared_responsibility_warning",
        "aws_iam_cli_list_policies",
        "aws_ec2_user_data_tip",
        "aws_concepts_scale_up_vs_out"
      ],
      "cycle": 1,
      "last_sent": "2026-04-11"
    },
    "teddy|j.t-elmacin@hotmail.fr": {
      "sent_ids": [
        "api_dotenv_warning",
        "python_devops_automation",
        "python_list_operations",
        "python_pip_freeze",
        "python_venv_setup",
        "api_gunicorn_prod",
        "python_packaging_warning",
        "api_curl_post_json",
        "python_psutil_install",
        "python_pytest_install",
        "python_global_warning",
        "python_subprocess_shell_warning_b",
        "python_security_warning",
        "python_gil_definition",
        "python_property_decorator",
        "python_dotenv_usage",
        "python_cprofile_command",
        "python_uvicorn_run",
        "python_file_error",
        "python_thread_example",
        "python_pathlib_tip",
        "python_install_linux",
        "python_asyncio_run",
        "api_spring_boot_run",
        "api_tail_logs",
        "python_versioning_tip",
        "python_multiprocessing_tip",
        "python_async_tip",
        "python_venv_activation",
        "python_datastructure_perf",
        "api_nodemon_hotreload",
        "python_orm_usage",
        "api_nvm_node_install",
        "python_falsy_values",
        "python_type_hint_basic",
        "api_flask_venv",
        "python_datetime_stamp",
        "python_poo_overengineering",
        "api_http_methods",
        "python_list_mutable_warning"
      ],
      "cycle": 1,
      "last_sent": "2026-04-11"
    }
  }
}